knx_frontend/__init__.py
knx_frontend/c.0fc42458.js
knx_frontend/c.0fc42458.js.gz
knx_frontend/c.42a97949.js
knx_frontend/c.42a97949.js.gz
knx_frontend/c.53796d6b.js
knx_frontend/c.53796d6b.js.gz
knx_frontend/c.9a9763d8.js
knx_frontend/c.9a9763d8.js.gz
knx_frontend/c.d971a0a5.js
knx_frontend/c.d971a0a5.js.gz
knx_frontend/c.e4ba960c.js
knx_frontend/c.e4ba960c.js.gz
knx_frontend/entrypoint.js
knx_frontend/main-f63f5335.js
knx_frontend/main-f63f5335.js.gz
knx_frontend/manifest.json
knx_frontend-20221026104517.dist-info/LICENSE
knx_frontend-20221026104517.dist-info/METADATA
knx_frontend-20221026104517.dist-info/WHEEL
knx_frontend-20221026104517.dist-info/top_level.txt
knx_frontend-20221026104517.dist-info/RECORD
