Metadata-Version: 2.1
Name: knx_frontend
Version: 20221026104517
Summary: The KNX Panel for the Home Assistant Frontend
Home-page: https://github.com/XKNX/knx-frontend
Download-URL: https://github.com/XKNX/knx-frontend/archive/20221026104517.zip
Author: Marvin Wichmann
Author-email: me@marvin-wichmann.de
License: MIT License
Keywords: knx panel xknx custom-panel home-assistant
Platform: any
Requires-Python: >=3.9.0
License-File: LICENSE
